openmetadata/__init__.py
openmetadata/helpers.py
openmetadata/api/__init__.py
openmetadata/api/apis_metadata.py
openmetadata/api/config.py
openmetadata/api/response.py
openmetadata/api/rest_api.py
openmetadata/api/utils.py
openmetadata/operations/__init__.py
openmetadata/operations/delete.py
openmetadata/operations/deploy.py
openmetadata/operations/kill_all.py
openmetadata/operations/last_dag_logs.py
openmetadata/operations/state.py
openmetadata/operations/status.py
openmetadata/operations/test_connection.py
openmetadata/operations/trigger.py
openmetadata/workflows/__init__.py
openmetadata/workflows/config.py
openmetadata/workflows/workflow_builder.py
openmetadata/workflows/workflow_factory.py
openmetadata/workflows/ingestion/__init__.py
openmetadata/workflows/ingestion/common.py
openmetadata/workflows/ingestion/metadata.py
openmetadata/workflows/ingestion/profiler.py
openmetadata/workflows/ingestion/registry.py
openmetadata/workflows/ingestion/usage.py
plugins/openmetadata_airflow_apis_plugin.py
openmetadata_airflow_managed_apis-0.11.5.3.dist-info/METADATA
openmetadata_airflow_managed_apis-0.11.5.3.dist-info/WHEEL
openmetadata_airflow_managed_apis-0.11.5.3.dist-info/top_level.txt
openmetadata_airflow_managed_apis-0.11.5.3.dist-info/RECORD
