Metadata-Version: 2.1
Name: openmetadata-airflow-managed-apis
Version: 0.11.5.3
Summary: Airflow REST APIs to create and manage DAGS
Home-page: https://open-metadata.org/
Author: OpenMetadata Committers
License: Apache License 2.0
Project-URL: Documentation, https://docs.open-metadata.org/
Project-URL: Source, https://github.com/open-metadata/OpenMetadata
Platform: UNKNOWN
Requires-Python: >=3.7
Requires-Dist: apache-airflow (==2.1.4)
Requires-Dist: openmetadata-ingestion[airflow-container] (~=0.11.5.3)
Requires-Dist: pendulum (~=2.1.2)
Requires-Dist: packaging (~=21.2)
Requires-Dist: Flask (~=1.1.4)
Requires-Dist: Flask-Admin (==1.6.0)
Requires-Dist: setuptools (~=58.3.0)
Provides-Extra: base
Requires-Dist: apache-airflow (==2.1.4) ; extra == 'base'
Requires-Dist: openmetadata-ingestion[airflow-container] (~=0.11.5.3) ; extra == 'base'
Requires-Dist: pendulum (~=2.1.2) ; extra == 'base'
Requires-Dist: packaging (~=21.2) ; extra == 'base'
Requires-Dist: Flask (~=1.1.4) ; extra == 'base'
Requires-Dist: Flask-Admin (==1.6.0) ; extra == 'base'
Requires-Dist: setuptools (~=58.3.0) ; extra == 'base'
Provides-Extra: dev
Requires-Dist: pytest ; extra == 'dev'
Requires-Dist: black (==21.12b0) ; extra == 'dev'
Requires-Dist: pytest-cov ; extra == 'dev'
Requires-Dist: isort ; extra == 'dev'
Requires-Dist: pylint ; extra == 'dev'
Requires-Dist: pycln ; extra == 'dev'
